[
  {
    "id": "d_01",
    "title": "Responsable Production (Câblage)",
    "company": "Yazaki Tanger",
    "location": "Tanger",
    "salary": "12.000 DH",
    "posted": "1h",
    "urgent": true,
    "isReal": true,
    "isDirect": true,
    "sourceName": "Direct HR",
    "email": "rh.tanger@yazaki-group.com",
    "catId": "cat_prod",
    "reqs": [
      "Bac+5 Ingénieur",
      "5 ans expérience",
      "Anglais courant"
    ]
  },
  {
    "id": "d_02",
    "title": "Vendeur Showroom",
    "company": "Marjane Market",
    "location": "Casablanca",
    "salary": "4.000 DH",
    "posted": "2h",
    "urgent": true,
    "isReal": true,
    "isDirect": true,
    "sourceName": "Direct HR",
    "email": "recrutement@marjane.co.ma",
    "catId": "cat_sales",
    "reqs": [
      "Niveau Bac",
      "Bonne présentation",
      "Dynamique"
    ]
  },
  {
    "id": "rek_0",
    "title": "Business Analyst - Asset Investissement (H/ F) | Casablanca (Maroc)",
    "company": "",
    "location": "Casablanca",
    "salary": "N/A",
    "posted": "Active",
    "urgent": false,
    "isReal": true,
    "isDirect": false,
    "sourceName": "Rekrute",
    "link": "https://www.rekrute.com/offre-emploi-business-analyst---asset-investissement-h-f-recrutement-confidentiel-casablanca-181992.html",
    "catId": "cat_prod"
  },
  {
    "id": "rek_1",
    "title": "Scientific Consultant - Spanish Speaker | Casablanca (Maroc)",
    "company": "Leyton",
    "location": "Casablanca",
    "salary": "N/A",
    "posted": "Active",
    "urgent": false,
    "isReal": true,
    "isDirect": false,
    "sourceName": "Rekrute",
    "link": "https://www.rekrute.com/offre-emploi-scientific-consultant---spanish-speaker-recrutement-leyton-casablanca-181991.html",
    "catId": "cat_admin"
  },
  {
    "id": "rek_2",
    "title": "Senior Data Scientist | Casablanca (Maroc)",
    "company": "Leyton",
    "location": "Casablanca",
    "salary": "N/A",
    "posted": "Active",
    "urgent": false,
    "isReal": true,
    "isDirect": false,
    "sourceName": "Rekrute",
    "link": "https://www.rekrute.com/offre-emploi-senior-data-scientist-recrutement-leyton-casablanca-181990.html",
    "catId": "cat_admin"
  },
  {
    "id": "rek_3",
    "title": "Architecte Technique / Solution (H/F) | Rabat, Rabat-Salé-Kénitra, Maroc (Maroc)",
    "company": "DXC - CDG",
    "location": "Rabat",
    "salary": "N/A",
    "posted": "Active",
    "urgent": false,
    "isReal": true,
    "isDirect": false,
    "sourceName": "Rekrute",
    "link": "https://www.rekrute.com/offre-emploi-architecte-technique-solution-hf-recrutement-dxc---cdg-rabat-rabat-sale-kenitra-maroc-181989.html",
    "catId": "cat_admin"
  },
  {
    "id": "rek_4",
    "title": "Administrateur des offres (F/H) | Casablanca (Maroc)",
    "company": "Sofrecom Maroc",
    "location": "Casablanca",
    "salary": "N/A",
    "posted": "Active",
    "urgent": false,
    "isReal": true,
    "isDirect": false,
    "sourceName": "Rekrute",
    "link": "https://www.rekrute.com/offre-emploi-administrateur-des-offres-fh-recrutement-sofrecom-maroc-casablanca-181988.html",
    "catId": "cat_admin"
  },
  {
    "id": "rek_5",
    "title": "Ingénieur Test Fonctionnel  Tests API Postman | Casablanca (Maroc)",
    "company": "Capgemini",
    "location": "Casablanca",
    "salary": "N/A",
    "posted": "Active",
    "urgent": false,
    "isReal": true,
    "isDirect": false,
    "sourceName": "Rekrute",
    "link": "https://www.rekrute.com/offre-emploi-ingenieur-test-fonctionnel-tests-api-postman-recrutement-capgemini-casablanca-181987.html",
    "catId": "cat_admin"
  },
  {
    "id": "rek_6",
    "title": "Conseiller clientèle bilingue (Francais/Anglais) | Casablanca (Maroc)",
    "company": "Atlas Online",
    "location": "Casablanca",
    "salary": "N/A",
    "posted": "Active",
    "urgent": false,
    "isReal": true,
    "isDirect": false,
    "sourceName": "Rekrute",
    "link": "https://www.rekrute.com/offre-emploi-conseiller-clientele-bilingue-francaisanglais-recrutement-atlas-online-casablanca-181237.html",
    "catId": "cat_call"
  },
  {
    "id": "rek_7",
    "title": "Chargés de clientèle Bilingue (Francais/Anglais) | Casablanca (Maroc)",
    "company": "Atlas Online",
    "location": "Casablanca",
    "salary": "N/A",
    "posted": "Active",
    "urgent": false,
    "isReal": true,
    "isDirect": false,
    "sourceName": "Rekrute",
    "link": "https://www.rekrute.com/offre-emploi-charges-de-clientele-bilingue-francaisanglais-recrutement-atlas-online-casablanca-180629.html",
    "catId": "cat_call"
  },
  {
    "id": "rek_8",
    "title": "Technicien Méthodes & Progrès | Tanger (Maroc)",
    "company": "Groupe Bel",
    "location": "Tanger",
    "salary": "N/A",
    "posted": "Active",
    "urgent": false,
    "isReal": true,
    "isDirect": false,
    "sourceName": "Rekrute",
    "link": "https://www.rekrute.com/offre-emploi-technicien-methodes-progres-recrutement-groupe-bel-tanger-179771.html",
    "catId": "cat_tech"
  },
  {
    "id": "rek_9",
    "title": "Technicien génie civil  (H/F) | Tanger (Maroc)",
    "company": "Groupe Bel",
    "location": "Tanger",
    "salary": "N/A",
    "posted": "Active",
    "urgent": false,
    "isReal": true,
    "isDirect": false,
    "sourceName": "Rekrute",
    "link": "https://www.rekrute.com/offre-emploi-technicien-genie-civil-hf-recrutement-groupe-bel-tanger-179770.html",
    "catId": "cat_tech"
  }
]