[
  {
    "id": "d_01",
    "title": "Responsable Production (Câblage)",
    "company": "Yazaki Tanger",
    "location": "Tanger",
    "salary": "12.000 DH",
    "posted": "1h",
    "urgent": true,
    "isReal": true,
    "isDirect": true,
    "sourceName": "Direct HR",
    "email": "rh.tanger@yazaki-group.com",
    "catId": "cat_prod",
    "reqs": [
      "Bac+5 Ingénieur",
      "5 ans expérience",
      "Anglais courant"
    ]
  },
  {
    "id": "d_02",
    "title": "Vendeur Showroom",
    "company": "Marjane Market",
    "location": "Casablanca",
    "salary": "4.000 DH",
    "posted": "2h",
    "urgent": true,
    "isReal": true,
    "isDirect": true,
    "sourceName": "Direct HR",
    "email": "recrutement@marjane.co.ma",
    "catId": "cat_sales",
    "reqs": [
      "Niveau Bac",
      "Bonne présentation",
      "Dynamique"
    ]
  },
  {
    "id": "rek_0",
    "title": "Carrossiers | Casablanca (Maroc)",
    "company": "Groupe Smeia",
    "location": "Casablanca",
    "salary": "N/A",
    "posted": "Active",
    "urgent": false,
    "isReal": true,
    "isDirect": false,
    "sourceName": "Rekrute",
    "link": "https://www.rekrute.com/offre-emploi-carrossiers-recrutement-groupe-smeia-casablanca-182659.html",
    "catId": "cat_admin"
  },
  {
    "id": "rek_1",
    "title": "Manager H/F | Meknès (Maroc)",
    "company": "McDonald's Maroc",
    "location": "Meknès",
    "salary": "N/A",
    "posted": "Active",
    "urgent": false,
    "isReal": true,
    "isDirect": false,
    "sourceName": "Rekrute",
    "link": "https://www.rekrute.com/offre-emploi-manager-hf-recrutement-mcdonalds-maroc-meknes-182658.html",
    "catId": "cat_admin"
  },
  {
    "id": "rek_2",
    "title": "Carrossiers | Rabat (Maroc)",
    "company": "Groupe Smeia",
    "location": "Rabat",
    "salary": "N/A",
    "posted": "Active",
    "urgent": false,
    "isReal": true,
    "isDirect": false,
    "sourceName": "Rekrute",
    "link": "https://www.rekrute.com/offre-emploi-carrossiers-recrutement-groupe-smeia-rabat-182657.html",
    "catId": "cat_admin"
  },
  {
    "id": "rek_3",
    "title": "Conseiller Service Après Vente | Casablanca (Maroc)",
    "company": "Groupe Smeia",
    "location": "Casablanca",
    "salary": "N/A",
    "posted": "Active",
    "urgent": false,
    "isReal": true,
    "isDirect": false,
    "sourceName": "Rekrute",
    "link": "https://www.rekrute.com/offre-emploi-conseiller-service-apres-vente-recrutement-groupe-smeia-casablanca-182656.html",
    "catId": "cat_sales"
  },
  {
    "id": "rek_4",
    "title": "Chef de Produit / Prix | Casablanca (Maroc)",
    "company": "Groupe Smeia",
    "location": "Casablanca",
    "salary": "N/A",
    "posted": "Active",
    "urgent": false,
    "isReal": true,
    "isDirect": false,
    "sourceName": "Rekrute",
    "link": "https://www.rekrute.com/offre-emploi-chef-de-produit-prix-recrutement-groupe-smeia-casablanca-182655.html",
    "catId": "cat_admin"
  },
  {
    "id": "rek_5",
    "title": "Chef de la Section Processus, AMOA et PMO | Casablanca (Maroc)",
    "company": "Groupe Smeia",
    "location": "Casablanca",
    "salary": "N/A",
    "posted": "Active",
    "urgent": false,
    "isReal": true,
    "isDirect": false,
    "sourceName": "Rekrute",
    "link": "https://www.rekrute.com/offre-emploi-chef-de-la-section-processus-amoa-et-pmo-recrutement-groupe-smeia-casablanca-182654.html",
    "catId": "cat_admin"
  },
  {
    "id": "rek_6",
    "title": "Chef de la Section Achats | Casablanca (Maroc)",
    "company": "Groupe Smeia",
    "location": "Casablanca",
    "salary": "N/A",
    "posted": "Active",
    "urgent": false,
    "isReal": true,
    "isDirect": false,
    "sourceName": "Rekrute",
    "link": "https://www.rekrute.com/offre-emploi-chef-de-la-section-achats-recrutement-groupe-smeia-casablanca-182653.html",
    "catId": "cat_admin"
  },
  {
    "id": "rek_7",
    "title": "Chef de la Section Réseaux et Télécommunications | Casablanca (Maroc)",
    "company": "Groupe Smeia",
    "location": "Casablanca",
    "salary": "N/A",
    "posted": "Active",
    "urgent": false,
    "isReal": true,
    "isDirect": false,
    "sourceName": "Rekrute",
    "link": "https://www.rekrute.com/offre-emploi-chef-de-la-section-reseaux-et-telecommunications-recrutement-groupe-smeia-casablanca-182652.html",
    "catId": "cat_it"
  },
  {
    "id": "rek_8",
    "title": "Chef de la Section Helpdesk et Support | Casablanca (Maroc)",
    "company": "Groupe Smeia",
    "location": "Casablanca",
    "salary": "N/A",
    "posted": "Active",
    "urgent": false,
    "isReal": true,
    "isDirect": false,
    "sourceName": "Rekrute",
    "link": "https://www.rekrute.com/offre-emploi-chef-de-la-section-helpdesk-et-support-recrutement-groupe-smeia-casablanca-182651.html",
    "catId": "cat_admin"
  },
  {
    "id": "rek_9",
    "title": "Chef de la Section Etudes et Développement SI | Casablanca (Maroc)",
    "company": "Groupe Smeia",
    "location": "Casablanca",
    "salary": "N/A",
    "posted": "Active",
    "urgent": false,
    "isReal": true,
    "isDirect": false,
    "sourceName": "Rekrute",
    "link": "https://www.rekrute.com/offre-emploi-chef-de-la-section-etudes-et-developpement-si-recrutement-groupe-smeia-casablanca-182650.html",
    "catId": "cat_admin"
  }
]