[
  {
    "id": "d_01",
    "title": "Responsable Production (Câblage)",
    "company": "Yazaki Tanger",
    "location": "Tanger",
    "salary": "12.000 DH",
    "posted": "1h",
    "urgent": true,
    "isReal": true,
    "isDirect": true,
    "sourceName": "Direct HR",
    "email": "rh.tanger@yazaki-group.com",
    "catId": "cat_prod",
    "reqs": [
      "Bac+5 Ingénieur",
      "5 ans expérience",
      "Anglais courant"
    ]
  },
  {
    "id": "d_02",
    "title": "Vendeur Showroom",
    "company": "Marjane Market",
    "location": "Casablanca",
    "salary": "4.000 DH",
    "posted": "2h",
    "urgent": true,
    "isReal": true,
    "isDirect": true,
    "sourceName": "Direct HR",
    "email": "recrutement@marjane.co.ma",
    "catId": "cat_sales",
    "reqs": [
      "Niveau Bac",
      "Bonne présentation",
      "Dynamique"
    ]
  },
  {
    "id": "rek_0",
    "title": "Gestionnaire Clientèle (H/F) | Marrakech/ Essaouira (Maroc)",
    "company": "Attijariwafa bank",
    "location": "Marrakech",
    "salary": "N/A",
    "posted": "Active",
    "urgent": false,
    "isReal": true,
    "isDirect": false,
    "sourceName": "Rekrute",
    "link": "https://www.rekrute.com/offre-emploi-gestionnaire-clientele-hf-recrutement-attijariwafa-bank-marrakech-essaouira-180301.html",
    "catId": "cat_admin"
  },
  {
    "id": "rek_1",
    "title": "Product Manager (H/F) | Casablanca (Maroc)",
    "company": "",
    "location": "Casablanca",
    "salary": "N/A",
    "posted": "Active",
    "urgent": false,
    "isReal": true,
    "isDirect": false,
    "sourceName": "Rekrute",
    "link": "https://www.rekrute.com/offre-emploi-product-manager-hf-recrutement-confidentiel-casablanca-180702.html",
    "catId": "cat_admin"
  },
  {
    "id": "rek_2",
    "title": "Business operations officer (H/F) | Casablanca (Maroc)",
    "company": "",
    "location": "Casablanca",
    "salary": "N/A",
    "posted": "Active",
    "urgent": false,
    "isReal": true,
    "isDirect": false,
    "sourceName": "Rekrute",
    "link": "https://www.rekrute.com/offre-emploi-business-operations-officer-hf-recrutement-confidentiel-casablanca-180703.html",
    "catId": "cat_prod"
  },
  {
    "id": "rek_3",
    "title": "Technicien BTP AUTOCAD | Casablanca (Maroc)",
    "company": "",
    "location": "Casablanca",
    "salary": "N/A",
    "posted": "Active",
    "urgent": false,
    "isReal": true,
    "isDirect": false,
    "sourceName": "Rekrute",
    "link": "https://www.rekrute.com/offre-emploi-technicien-btp-autocad-recrutement-confidentiel-casablanca-180570.html",
    "catId": "cat_tech"
  },
  {
    "id": "rek_4",
    "title": "Ingénieur Commercial – Solutions Plasturgie · Maroc | Casablanca (Maroc)",
    "company": "ORH Assessment",
    "location": "Casablanca",
    "salary": "N/A",
    "posted": "Active",
    "urgent": false,
    "isReal": true,
    "isDirect": false,
    "sourceName": "Rekrute",
    "link": "https://www.rekrute.com/offre-emploi-ingenieur-commercial-solutions-plasturgie-maroc-recrutement-orh-assessment-casablanca-181649.html",
    "catId": "cat_sales"
  },
  {
    "id": "rek_5",
    "title": "ExeKutiveDirecteur des Opérations en charge de la restauration | Marrakech (Maroc)",
    "company": "Es Saadi Marrakech Resort",
    "location": "Marrakech",
    "salary": "N/A",
    "posted": "Active",
    "urgent": false,
    "isReal": true,
    "isDirect": false,
    "sourceName": "Rekrute",
    "link": "https://www.rekrute.com/offre-emploi-directeur-des-operations-en-charge-de-la-restauration-recrutement-es-saadi-marrakech-resort-marrakech-180002.html",
    "catId": "cat_admin"
  },
  {
    "id": "rek_6",
    "title": "Commercial Senior Grands Comptes F/H - Avec expérience en assurance | Casablanca (Maroc)",
    "company": "HEOMI",
    "location": "Casablanca",
    "salary": "N/A",
    "posted": "Active",
    "urgent": false,
    "isReal": true,
    "isDirect": false,
    "sourceName": "Rekrute",
    "link": "https://www.rekrute.com/offre-emploi-commercial-senior-grands-comptes-fh---avec-experience-en-assurance-recrutement-heomi-casablanca-181459.html",
    "catId": "cat_sales"
  },
  {
    "id": "rek_7",
    "title": "Bilingual E-chat Agents | Rabat (Maroc)",
    "company": "Cnexia",
    "location": "Rabat",
    "salary": "N/A",
    "posted": "Active",
    "urgent": false,
    "isReal": true,
    "isDirect": false,
    "sourceName": "Rekrute",
    "link": "https://www.rekrute.com/offre-emploi-bilingual-e-chat-agents-recrutement-cnexia-rabat-181646.html",
    "catId": "cat_admin"
  },
  {
    "id": "rek_8",
    "title": "Bilingual (fr/en) customer service & upselling representatives - order tracking - rabat | Rabat (Maroc)",
    "company": "Cnexia",
    "location": "Rabat",
    "salary": "N/A",
    "posted": "Active",
    "urgent": false,
    "isReal": true,
    "isDirect": false,
    "sourceName": "Rekrute",
    "link": "https://www.rekrute.com/offre-emploi-bilingual-fren-customer-service-upselling-representatives---order-tracking---rabat-recrutement-cnexia-rabat-181645.html",
    "catId": "cat_admin"
  },
  {
    "id": "rek_9",
    "title": "Kinésithérapeute | Rabat (Maroc)",
    "company": "APEE - Association pour la Promotion de l’Enseignement d’Excellence",
    "location": "Rabat",
    "salary": "N/A",
    "posted": "Active",
    "urgent": false,
    "isReal": true,
    "isDirect": false,
    "sourceName": "Rekrute",
    "link": "https://www.rekrute.com/offre-emploi-kinesitherapeute-recrutement-apee---association-pour-la-promotion-de-lenseignement-dexcellence-rabat-181370.html",
    "catId": "cat_admin"
  }
]